krisolis_utilities/__init__.py
krisolis_utilities/utils.py
krisolis_utilities-0.11.dist-info/METADATA
krisolis_utilities-0.11.dist-info/WHEEL
krisolis_utilities-0.11.dist-info/top_level.txt
krisolis_utilities-0.11.dist-info/RECORD
